pyright_to_gitlab_ci/__init__.py
pyright_to_gitlab_ci/main.py
pyright_to_gitlab_ci-1.1.0.dist-info/licenses/LICENSE
tests/test_reports_conversion.py
tests/reports/assert1.py
pyright_to_gitlab_ci-1.1.0.dist-info/METADATA
pyright_to_gitlab_ci-1.1.0.dist-info/WHEEL
pyright_to_gitlab_ci-1.1.0.dist-info/entry_points.txt
pyright_to_gitlab_ci-1.1.0.dist-info/top_level.txt
pyright_to_gitlab_ci-1.1.0.dist-info/RECORD
