Metadata-Version: 2.4
Name: pyright-to-gitlab-ci
Version: 1.1.0
Summary: Port of the NPM package of the same name
License-Expression: Apache-2.0
Project-URL: Repository, https://gitlab.com/leogermond/pyright-to-gitlab-ci
Requires-Python: >=3.10
License-File: LICENSE
Dynamic: license-file
